CHANGES.rst
MANIFEST.in
README.rst
requirements.txt
setup.py
sc_generate_hash.egg-info/PKG-INFO
sc_generate_hash.egg-info/SOURCES.txt
sc_generate_hash.egg-info/dependency_links.txt
sc_generate_hash.egg-info/entry_points.txt
sc_generate_hash.egg-info/requires.txt
sc_generate_hash.egg-info/top_level.txt
sc_hash/__init__.py
sc_hash/hash_utils.py
sc_hash/main.py
sc_hash/utils.py
sc_hash/configs/__init__.py
sc_hash/configs/default.py
sc_hash/tests/__init__.py
sc_hash/tests/sample_config/default.yml